libname/__init__.py
libname/hello.py
teghoshal-0.0.1.dist-info/METADATA
teghoshal-0.0.1.dist-info/WHEEL
teghoshal-0.0.1.dist-info/top_level.txt
teghoshal-0.0.1.dist-info/RECORD
